[
  {
    "name": "Leg Extension",
    "body part": "Legs",
    "level": "Novice",
    "repetitions": "15-20",
    "sets": "2"
  },
  {
    "name": "Leg Curl",
    "body part": "Legs",
    "level": "Novice",
    "repetitions": "15-20",
    "sets": "2"
  },
  {
    "name": "Chest Fly",
    "body part": "Chest",
    "level": "Novice",
    "repetitions": "15-20",
    "sets": "2"
  },
  {
    "name": "Machine Press",
    "body part": "Chest",
    "level": "Novice",
    "repetitions": "15-20",
    "sets": "2"
  },
  {
    "name": "Lat Pulldown",
    "body part": "Back",
    "level": "Novice",
    "repetitions": "15-20",
    "sets": "2"
  },
  {
    "name": "Machine Row",
    "body part": "Back",
    "level": "Novice",
    "repetitions": "15-20",
    "sets": "2"
  },
  {
    "name": "Lateral Raises",
    "body part": "Shoulders",
    "level": "Novice",
    "repetitions": "15-20",
    "sets": "2"
  },
  {
    "name": "Shoulder Press",
    "body part": "Shoulders",
    "level": "Novice",
    "repetitions": "15-20",
    "sets": "2"
  },
  {
    "name": "Hammer Curl",
    "body part": "Biceps",
    "level": "Novice",
    "repetitions": "15-20",
    "sets": "2"
  },
  {
    "name": "Machine Curl",
    "body part": "Biceps",
    "level": "Novice",
    "repetitions": "15-20",
    "sets": "2"
  },
  {
    "name": "Pressdowns",
    "body part": "Triceps",
    "level": "Novice",
    "repetitions": "15-20",
    "sets": "2"
  },
  {
    "name": "Seated Dips",
    "body part": "Triceps",
    "level": "Novice",
    "repetitions": "15-20",
    "sets": "2"
  },
  {
    "name": "Crunches",
    "body part": "Abs",
    "level": "Novice",
    "repetitions": "15-20",
    "sets": "2"
  },
  {
    "name": "Leg Lifts",
    "body part": "Abs",
    "level": "Novice",
    "repetitions": "15-20",
    "sets": "2"
  }
]
